mkdocs_azure_pipelines/__init__.py
mkdocs_azure_pipelines/ado_pipe_to_md.py
mkdocs_azure_pipelines/cli.py
mkdocs_azure_pipelines/plugin.py
mkdocs_azure_pipelines-0.1.3.dist-info/METADATA
mkdocs_azure_pipelines-0.1.3.dist-info/WHEEL
mkdocs_azure_pipelines-0.1.3.dist-info/entry_points.txt
mkdocs_azure_pipelines-0.1.3.dist-info/licenses/LICENSE
mkdocs_azure_pipelines-0.1.3.dist-info/RECORD
