Metadata-Version: 2.4
Name: mkdocs-azure-pipelines
Version: 0.1.3
Summary: MkDocs plugin to generate documentation for Azure Pipelines/Templates
Project-URL: Repository, https://github.com/Wesztman/mkdocs-azure-pipelines
Author-email: Carl Westman <carl.westman91@gmail.com>
License: MIT License
License-File: LICENSE
Requires-Python: >=3.10
Requires-Dist: mkdocs~=1.6.1
Requires-Dist: ruamel-yaml>=0.18.10
